AUTHORS
MANIFEST.in
README.md
TERMS.txt
setup.py
django_widgeter.egg-info/PKG-INFO
django_widgeter.egg-info/SOURCES.txt
django_widgeter.egg-info/dependency_links.txt
django_widgeter.egg-info/not-zip-safe
django_widgeter.egg-info/top_level.txt
widgeter/__init__.py
widgeter/base.py
widgeter/models.py
widgeter/registry.py
widgeter/tests.py
widgeter/views.py
widgeter/templatetags/__init__.py
widgeter/templatetags/widgeter.py