Metadata-Version: 1.1
Name: django-widgeter
Version: 0.1
Summary: Widgeter: A simple engine for backend widgets
Home-page: http://github.com/dlapiduz/django-widgeter
Author: Diego Lapiduz
Author-email: diego@lapiduz.com
License: Public Domain
Platform: UNKNOWN
Classifier: Topic :: Internet :: WWW/HTTP :: Dynamic Content
Classifier: Intended Audience :: Developers
Classifier: Programming Language :: Python
Classifier: Programming Language :: Python :: 2.6
Classifier: Programming Language :: Python :: 2.7
Classifier: Framework :: Django
Classifier: Development Status :: 4 - Beta
Classifier: Operating System :: OS Independent
